testfully-0.4.0.dist-info/METADATA
testfully-0.4.0.dist-info/WHEEL
testfully/validator.py
testfully/__init__.py
testfully/tracker.py
testfully/testfully.abi3.so
testfully-0.4.0.dist-info/RECORD
